{
  "db_name": "PostgreSQL",
  "query": "\n        INSERT INTO checkin_open_responses (\n            id,\n            user_id,\n            checkin_id,\n            question_id,\n            question_type,\n            response_source,\n            enc_response,\n            enc_ai_analysis,\n            risk_score,\n            urgent,\n            audio_duration_seconds\n        )\n        VALUES ($1, $2, $3, $4, $5, $6, $7, $8, $9, $10, $11)\n        ",
  "describe": {
    "columns": [],
    "parameters": {
      "Left": [
        "Uuid",
        "Uuid",
        "Text",
        "Int4",
        "Varchar",
        "Text",
        "Text",
        "Text",
        "Int2",
        "Bool",
        "Int4"
      ]
    },
    "nullable": []
  },
  "hash": "b82144bace88fdffd2549894e42b2d7066ba51c7db04f9464c6357e8a31dab33"
}
